{
    "status": {
        "d_18": {
            "yes": 236,
            "no": 0,
            "undecided": 164,
            "unknown": 1936,
            "pyes": 0.0004170177683361769,
            "pno": 0.0,
            "pundecided": 0.005896154927957875,
            "punknown": 0.02829751215200933,
            "time": 55.49735450744629,
            "percY": 2839.08,
            "percN": 0.0,
            "percU": 1972.92,
            "percUNK": 23290.08,
            "l": 0.0004170177683361769,
            "u": 1.0
        },
        "~a_7": {
            "yes": 78,
            "no": 172,
            "undecided": 2050,
            "unknown": 36,
            "pyes": 1.6447508208970317e-07,
            "pno": 9.270919103836747e-06,
            "pundecided": 0.03460121178361324,
            "punknown": 3.7670504200482264e-08,
            "time": 56.088679790496826,
            "percY": 938.34,
            "percN": 2069.16,
            "percU": 24661.5,
            "percUNK": 433.08,
            "l": 1.6447508208970317e-07,
            "u": 0.9999907290808961
        }
    },
    "data": {
        "n_samples": 1203,
        "time": 108.86635708808899,
        "repeated_programs": 35,
        "inconsistent_programs": 0,
        "worlds_consulted": 12425
    }
}