{
    "status": {
        "a_7": {
            "yes": 455,
            "no": 0,
            "undecided": 0,
            "unknown": 292,
            "pyes": 0.5436391986370602,
            "pno": 0.0,
            "pundecided": 0.0,
            "punknown": 0.010927216045951236,
            "time": 17.125460147857666,
            "percY": 3726.45,
            "percN": 0.0,
            "percU": 0.0,
            "percUNK": 2391.48,
            "l": 0.5436391986370602,
            "u": 1.0,
            "flag": "INTEREST"
        },
        "a_16": {
            "yes": 67,
            "no": 284,
            "undecided": 395,
            "unknown": 1,
            "pyes": 0.0002539922110360502,
            "pno": 0.00982026184010513,
            "pundecided": 0.5444921566658051,
            "punknown": 3.966064875601921e-09,
            "time": 17.874727725982666,
            "percY": 548.73,
            "percN": 2325.96,
            "percU": 3235.05,
            "percUNK": 8.19,
            "l": 0.0002539922110360502,
            "u": 0.9901797381598949
        },
        "~a_18": {
            "yes": 231,
            "no": 125,
            "undecided": 390,
            "unknown": 1,
            "pyes": 0.005073775628851304,
            "pno": 0.00686915045379294,
            "pundecided": 0.5426218878635841,
            "punknown": 1.600736782448886e-06,
            "time": 17.513786554336548,
            "percY": 1891.89,
            "percN": 1023.75,
            "percU": 3194.1,
            "percUNK": 8.19,
            "l": 0.005073775628851304,
            "u": 0.993130849546207
        }
    },
    "data": {
        "n_samples": 819,
        "time": 54.130924701690674,
        "repeated_worlds": 72,
        "repeated_progs": 72,
        "unique_progs": 747
    }
}