{
    "status": {
        "~d_17": {
            "yes": 15595,
            "no": 0,
            "undecided": 5834,
            "unknown": 3503,
            "pyes": 0.08586851013467224,
            "pno": 0.0,
            "pundecided": 0.0004713507169098982,
            "punknown": 0.00043397923331549927,
            "time": 546.1562731266022,
            "percY": 4088073.3,
            "percN": 0.0,
            "percU": 1529324.76,
            "percUNK": 918276.42,
            "l": 0.08586851013467224,
            "u": 1.0
        },
        "a_7": {
            "yes": 4670,
            "no": 6264,
            "undecided": 13279,
            "unknown": 719,
            "pyes": 0.004953799724054136,
            "pno": 0.07180445081198979,
            "pundecided": 0.004826711359607445,
            "punknown": 0.005188878189246488,
            "time": 549.8464741706848,
            "percY": 1224193.8,
            "percN": 1642044.96,
            "percU": 3480957.06,
            "percUNK": 188478.66,
            "l": 0.004953799724054136,
            "u": 0.9281955491880102
        },
        "~a_8": {
            "yes": 9174,
            "no": 3777,
            "undecided": 11950,
            "unknown": 31,
            "pyes": 0.08086939360675328,
            "pno": 0.0016622943112249158,
            "pundecided": 0.004242152093160453,
            "punknown": 7.375908305519222e-11,
            "time": 549.2414383888245,
            "percY": 2404872.36,
            "percN": 990102.78,
            "percU": 3132573.0,
            "percUNK": 8126.34,
            "l": 0.08086939360675328,
            "u": 0.9983377056887751
        }
    },
    "data": {
        "n_samples": 26214,
        "time": 1683.3862726688385,
        "repeated_worlds": 1282,
        "repeated_progs": 10783,
        "unique_progs": 15431
    }
}