{
    "status": {
        "d_11": {
            "yes": 15695,
            "no": 0,
            "undecided": 1135,
            "unknown": 8067,
            "pyes": 0.007847983735749235,
            "pno": 0.0,
            "pundecided": 0.00026610564638256996,
            "punknown": 0.03201759820116333,
            "time": 430.064932346344,
            "percY": 4114287.3,
            "percN": 0.0,
            "percU": 297528.9,
            "percUNK": 2114683.38,
            "l": 0.007847983735749235,
            "u": 1.0
        },
        "a_7": {
            "yes": 342,
            "no": 1304,
            "undecided": 22963,
            "unknown": 288,
            "pyes": 8.826713762994404e-05,
            "pno": 0.00045247307388747833,
            "pundecided": 0.039428397386951065,
            "punknown": 0.00016254998482633475,
            "time": 429.4626660346985,
            "percY": 89651.88,
            "percN": 341830.56,
            "percU": 6019520.82,
            "percUNK": 75496.32,
            "l": 8.826713762994404e-05,
            "u": 0.9995475269261125
        }
    },
    "data": {
        "n_samples": 26214,
        "time": 894.6690685749054,
        "repeated_worlds": 1317,
        "repeated_progs": 13406,
        "unique_progs": 12808
    }
}