{
    "status": {
        "~a_0": {
            "yes": 798949,
            "no": 0,
            "undecided": 0,
            "unknown": 797091,
            "pyes": 0.07314082350282884,
            "pno": 0.0,
            "pundecided": 0.0,
            "punknown": 0.026399067412321425,
            "time": 166.44246411323547,
            "percY": 13404135152.29,
            "percN": 0.0,
            "percU": 0.0,
            "percUNK": 13372963096.11,
            "l": 0.07314082350282884,
            "u": 1.0
        },
        "a_7": {
            "yes": 623038,
            "no": 174654,
            "undecided": 798348,
            "unknown": 0,
            "pyes": 0.03368345623868931,
            "pno": 0.0031682400141399255,
            "pundecided": 0.06268819466232094,
            "punknown": 0.0,
            "time": 167.32967805862427,
            "percY": 10452839363.98,
            "percN": 2930206835.34,
            "percU": 13394052049.08,
            "percUNK": 0.0,
            "l": 0.03368345623868931,
            "u": 0.99683175998586
        },
        "~a_7": {
            "yes": 174654,
            "no": 623038,
            "undecided": 798348,
            "unknown": 0,
            "pyes": 0.0031682400141399255,
            "pno": 0.03368345623868931,
            "pundecided": 0.06268819466232094,
            "punknown": 0.0,
            "time": 167.78626561164856,
            "percY": 2930206835.34,
            "percN": 10452839363.98,
            "percU": 13394052049.08,
            "percUNK": 0.0,
            "l": 0.0031682400141399255,
            "u": 0.9663165437613107
        }
    },
    "data": {
        "n_samples": 1677721,
        "time": 1449.873524427414,
        "repeated_worlds": 81681,
        "repeated_progs": 1673625,
        "unique_progs": 4096
    }
}