{
    "status": {
        "~d_16": {
            "yes": 797679,
            "no": 0,
            "undecided": 798532,
            "unknown": 0,
            "pyes": 0.06229380101065709,
            "pno": 0.0,
            "pundecided": 0.03496420069628076,
            "punknown": 0.0,
            "time": 39.973023891448975,
            "percY": 13382828095.59,
            "percN": 0.0,
            "percU": 13397139055.72,
            "percUNK": 0.0,
            "l": 0.06229380101065709,
            "u": 1.0
        },
        "a_5": {
            "yes": 797224,
            "no": 0,
            "undecided": 798987,
            "unknown": 0,
            "pyes": 0.040076118678300104,
            "pno": 0.0,
            "pundecided": 0.0571818830286366,
            "punknown": 0.0,
            "time": 39.981393575668335,
            "percY": 13375194465.04,
            "percN": 0.0,
            "percU": 13404772686.27,
            "percUNK": 0.0,
            "l": 0.040076118678300104,
            "u": 1.0
        },
        "~a_8": {
            "yes": 336587,
            "no": 262181,
            "undecided": 997443,
            "unknown": 0,
            "pyes": 0.03950622441184324,
            "pno": 0.01073940821991828,
            "pundecided": 0.047012369075174004,
            "punknown": 0.0,
            "time": 40.707120418548584,
            "percY": 5646990782.27,
            "percN": 4398665695.01,
            "percU": 16734310674.03,
            "percUNK": 0.0,
            "l": 0.03950622441184324,
            "u": 0.9892605917800817
        }
    },
    "data": {
        "n_samples": 1677721,
        "time": 945.6010046005249,
        "repeated_worlds": 81510,
        "repeated_progs": 1676697,
        "unique_progs": 1024
    }
}