{
    "status": {
        "d_10": {
            "yes": 1495,
            "no": 0,
            "undecided": 5,
            "unknown": 47,
            "pyes": 0.9848591601157458,
            "pno": 0.0,
            "pundecided": 1.0738408314725826e-05,
            "punknown": 0.002357006752213192,
            "time": 25.83520007133484,
            "percY": 783798.6,
            "percN": 0.0,
            "percU": 2621.4,
            "percUNK": 24641.16,
            "l": 0.9848591601157458,
            "u": 1.0,
            "flag": "INTEREST"
        },
        "a_6": {
            "yes": 241,
            "no": 0,
            "undecided": 299,
            "unknown": 1007,
            "pyes": 0.07535831705843675,
            "pno": 0.0,
            "pundecided": 0.04908256564798717,
            "punknown": 0.8627860225698499,
            "time": 25.801844120025635,
            "percY": 126351.48,
            "percN": 0.0,
            "percU": 156759.72,
            "percUNK": 527949.96,
            "l": 0.07535831705843675,
            "u": 1.0
        },
        "~a_8": {
            "yes": 26,
            "no": 214,
            "undecided": 1307,
            "unknown": 0,
            "pyes": 0.0016937549906774682,
            "pno": 0.041596711763342176,
            "pundecided": 0.9439364385222534,
            "punknown": 0.0,
            "time": 25.7139835357666,
            "percY": 13631.28,
            "percN": 112195.92,
            "percU": 685233.96,
            "percUNK": 0.0,
            "l": 0.0016937549906774682,
            "u": 0.9584032882366578
        }
    },
    "data": {
        "n_samples": 52428,
        "time": 79.45714950561523,
        "repeated_worlds": 50881,
        "repeated_progs": 51747,
        "unique_progs": 681
    }
}