{
    "status": {
        "~d_48": {
            "yes": 1024,
            "no": 0,
            "undecided": 3072,
            "unknown": 0,
            "pyes": 0.020832000000000024,
            "pno": 0.0,
            "pundecided": 0.9791680000000001,
            "punknown": 0.0,
            "time": 140.095698595047,
            "percY": 41943.04,
            "percN": 0.0,
            "percU": 125829.12,
            "percUNK": 0.0,
            "l": 0.020832000000000024,
            "u": 1.0
        },
        "a_16": {
            "yes": 880,
            "no": 824,
            "undecided": 2392,
            "unknown": 0,
            "pyes": 0.00832403890408552,
            "pno": 0.00935475804727584,
            "pundecided": 0.9823212030486402,
            "punknown": 0.0,
            "time": 162.10735368728638,
            "percY": 36044.8,
            "percN": 33751.04,
            "percU": 97976.32,
            "percUNK": 0.0,
            "l": 0.00832403890408552,
            "u": 0.9906452419527242
        }
    },
    "data": {
        "n_samples": 4096,
        "time": 471.7187194824219,
        "repeated_worlds": 0,
        "repeated_progs": 164,
        "unique_progs": 3932
    }
}