{
    "status": {
        "~d_15": {
            "yes": 102,
            "no": 0,
            "undecided": 88,
            "unknown": 0,
            "pyes": 0.000586935219359635,
            "pno": 0.0,
            "pundecided": 0.12516313037283525,
            "punknown": 0.0,
            "time": 5.726490497589111,
            "percY": 98.94,
            "percN": 0.0,
            "percU": 85.36,
            "percUNK": 0.0,
            "l": 0.000586935219359635,
            "u": 1.0
        },
        "~a_6": {
            "yes": 92,
            "no": 0,
            "undecided": 98,
            "unknown": 0,
            "pyes": 0.0001766999175855866,
            "pno": 0.0,
            "pundecided": 0.1255733656746093,
            "punknown": 0.0,
            "time": 5.738244533538818,
            "percY": 89.24,
            "percN": 0.0,
            "percU": 95.06,
            "percUNK": 0.0,
            "l": 0.0001766999175855866,
            "u": 1.0
        },
        "~a_7": {
            "yes": 6,
            "no": 82,
            "undecided": 102,
            "unknown": 0,
            "pyes": 3.1334517123865904e-07,
            "pno": 0.03211841517027694,
            "pundecided": 0.09363133707674672,
            "punknown": 0.0,
            "time": 5.999914169311523,
            "percY": 5.82,
            "percN": 79.54,
            "percU": 98.94,
            "percUNK": 0.0,
            "l": 3.1334517123865904e-07,
            "u": 0.9678815848297231
        }
    },
    "data": {
        "n_samples": 97,
        "time": 18.953226566314697,
        "repeated_programs": 2,
        "inconsistent_programs": 0,
        "worlds_consulted": 6756
    }
}