{
    "status": {
        "d_17": {
            "yes": 2048,
            "no": 0,
            "undecided": 2048,
            "unknown": 0,
            "pyes": 0.08000000000000004,
            "pno": 0.0,
            "pundecided": 0.9199999999999993,
            "punknown": 0.0,
            "time": 1.5732808113098145,
            "percY": 83886.08,
            "percN": 0.0,
            "percU": 83886.08,
            "percUNK": 0.0,
            "l": 0.08000000000000004,
            "u": 1.0
        },
        "a_5": {
            "yes": 2048,
            "no": 0,
            "undecided": 2048,
            "unknown": 0,
            "pyes": 0.8430750399999992,
            "pno": 0.0,
            "pundecided": 0.15692496000000009,
            "punknown": 0.0,
            "time": 1.5677390098571777,
            "percY": 83886.08,
            "percN": 0.0,
            "percU": 83886.08,
            "percUNK": 0.0,
            "l": 0.8430750399999992,
            "u": 1.0,
            "flag": "INTEREST"
        },
        "~a_7": {
            "yes": 896,
            "no": 1152,
            "undecided": 2048,
            "unknown": 0,
            "pyes": 0.8023084828972705,
            "pno": 0.04076655710272772,
            "pundecided": 0.15692496000000009,
            "punknown": 0.0,
            "time": 1.633845329284668,
            "percY": 36700.16,
            "percN": 47185.92,
            "percU": 83886.08,
            "percUNK": 0.0,
            "l": 0.8023084828972705,
            "u": 0.9592334428972723,
            "flag": "INTEREST"
        }
    },
    "data": {
        "n_samples": 4096,
        "time": 5.962728023529053,
        "repeated_worlds": 0,
        "repeated_progs": 4032,
        "unique_progs": 64
    }
}