{
    "status": {
        "a_2": {
            "yes": 11212,
            "no": 0,
            "undecided": 0,
            "unknown": 1584,
            "pyes": 0.0029069953489896114,
            "pno": 0.0,
            "pundecided": 0.0,
            "punknown": 0.07366465102879227,
            "time": 192.55679988861084,
            "percY": 1469556.84,
            "percN": 0.0,
            "percU": 0.0,
            "percUNK": 207614.88,
            "l": 0.0029069953489896114,
            "u": 1.0
        },
        "a_5": {
            "yes": 962,
            "no": 0,
            "undecided": 11650,
            "unknown": 184,
            "pyes": 4.848290344419549e-05,
            "pno": 0.0,
            "pundecided": 0.07652308549203458,
            "punknown": 7.798230253928228e-08,
            "time": 191.86311531066895,
            "percY": 126089.34,
            "percN": 0.0,
            "percU": 1526965.5,
            "percUNK": 24116.88,
            "l": 4.848290344419549e-05,
            "u": 1.0
        },
        "~a_7": {
            "yes": 390,
            "no": 588,
            "undecided": 11818,
            "unknown": 0,
            "pyes": 4.719653978897344e-06,
            "pno": 2.5037658850053078e-05,
            "pundecided": 0.07654188906495242,
            "punknown": 0.0,
            "time": 193.5409824848175,
            "percY": 51117.3,
            "percN": 77069.16,
            "percU": 1548985.26,
            "percUNK": 0.0,
            "l": 4.719653978897344e-06,
            "u": 0.9999749623411499
        }
    },
    "data": {
        "n_samples": 13107,
        "time": 594.1499235630035,
        "repeated_worlds": 311,
        "repeated_progs": 5721,
        "unique_progs": 7386
    }
}