{
    "status": {
        "~d_16": {
            "yes": 242,
            "no": 0,
            "undecided": 21,
            "unknown": 133,
            "pyes": 0.005617164069912419,
            "pno": 0.0,
            "pundecided": 4.4363725843552176e-05,
            "punknown": 0.04127514087235247,
            "time": 10.187050342559814,
            "percY": 989.78,
            "percN": 0.0,
            "percU": 85.89,
            "percUNK": 543.97,
            "l": 0.005617164069912419,
            "u": 1.0
        },
        "a_5": {
            "yes": 311,
            "no": 0,
            "undecided": 76,
            "unknown": 9,
            "pyes": 0.011121660737487679,
            "pno": 0.0,
            "pundecided": 0.035805940081372535,
            "punknown": 9.06784924823593e-06,
            "time": 10.29660415649414,
            "percY": 1271.99,
            "percN": 0.0,
            "percU": 310.84,
            "percUNK": 36.81,
            "l": 0.011121660737487679,
            "u": 1.0
        },
        "~a_7": {
            "yes": 49,
            "no": 288,
            "undecided": 57,
            "unknown": 2,
            "pyes": 0.00014126985181801754,
            "pno": 0.010986115035754283,
            "pundecided": 0.03580029008785815,
            "punknown": 8.993692677985247e-06,
            "time": 10.43112587928772,
            "percY": 200.41,
            "percN": 1177.92,
            "percU": 233.13,
            "percUNK": 8.18,
            "l": 0.00014126985181801754,
            "u": 0.9890138849642457
        }
    },
    "data": {
        "n_samples": 409,
        "time": 31.463819980621338,
        "repeated_worlds": 13,
        "repeated_progs": 97,
        "unique_progs": 312
    }
}