{
    "status": {
        "~a_1": {
            "yes": 348,
            "no": 0,
            "undecided": 0,
            "unknown": 42,
            "pyes": 0.14734846421218198,
            "pno": 0.0,
            "pundecided": 0.0,
            "punknown": 1.8458991992206442e-05,
            "time": 8.0354642868042,
            "percY": 1423.32,
            "percN": 0.0,
            "percU": 0.0,
            "percUNK": 171.78,
            "l": 0.14734846421218198,
            "u": 1.0
        },
        "a_5": {
            "yes": 199,
            "no": 0,
            "undecided": 181,
            "unknown": 10,
            "pyes": 0.10362694631754664,
            "pno": 0.0,
            "pundecided": 0.0437399656880941,
            "punknown": 1.1198533500000003e-08,
            "time": 8.093729972839355,
            "percY": 813.91,
            "percN": 0.0,
            "percU": 740.29,
            "percUNK": 40.9,
            "l": 0.10362694631754664,
            "u": 1.0
        },
        "~a_8": {
            "yes": 96,
            "no": 98,
            "undecided": 172,
            "unknown": 24,
            "pyes": 0.00035662311194501384,
            "pno": 0.09816316800000095,
            "pundecided": 0.04884153011966392,
            "punknown": 5.601972564342001e-06,
            "time": 8.1237051486969,
            "percY": 392.64,
            "percN": 400.82,
            "percU": 703.48,
            "percUNK": 98.16,
            "l": 0.00035662311194501384,
            "u": 0.9018368319999991
        }
    },
    "data": {
        "n_samples": 409,
        "time": 24.728933095932007,
        "repeated_worlds": 19,
        "repeated_progs": 66,
        "unique_progs": 343
    }
}