{
    "status": {
        "d_12": {
            "yes": 243,
            "no": 0,
            "undecided": 94,
            "unknown": 53,
            "pyes": 0.020903005873057663,
            "pno": 0.0,
            "pundecided": 0.0005397839406297454,
            "punknown": 1.3479853570861215e-05,
            "time": 10.505867719650269,
            "percY": 993.87,
            "percN": 0.0,
            "percU": 384.46,
            "percUNK": 216.77,
            "l": 0.020903005873057663,
            "u": 1.0
        },
        "~a_7": {
            "yes": 134,
            "no": 9,
            "undecided": 238,
            "unknown": 9,
            "pyes": 0.0025984580786724007,
            "pno": 2.3585868334415438e-05,
            "pundecided": 0.01883421841687264,
            "punknown": 7.303378803840004e-09,
            "time": 10.34117579460144,
            "percY": 548.06,
            "percN": 36.81,
            "percU": 973.42,
            "percUNK": 36.81,
            "l": 0.0025984580786724007,
            "u": 0.9999764141316656
        },
        "~a_8": {
            "yes": 24,
            "no": 152,
            "undecided": 204,
            "unknown": 10,
            "pyes": 0.0003857933514541323,
            "pno": 0.004909553598438718,
            "pundecided": 0.01615890579008546,
            "punknown": 2.016927279948652e-06,
            "time": 10.422482013702393,
            "percY": 98.16,
            "percN": 621.68,
            "percU": 834.36,
            "percUNK": 40.9,
            "l": 0.0003857933514541323,
            "u": 0.9950904464015613
        }
    },
    "data": {
        "n_samples": 409,
        "time": 31.834205865859985,
        "repeated_worlds": 19,
        "repeated_progs": 34,
        "unique_progs": 375
    }
}