{
    "status": {
        "~d_17": {
            "yes": 127736,
            "no": 0,
            "undecided": 0,
            "unknown": 0,
            "pyes": 0.9201726772276702,
            "pno": 0.0,
            "pundecided": 0.0,
            "punknown": 0.0,
            "time": 47.90288162231445,
            "percY": 1071526209.6,
            "percN": 0.0,
            "percU": 0.0,
            "percUNK": 0.0,
            "l": 0.9201726772276702,
            "u": 1.0,
            "flag": "INTEREST"
        },
        "a_7": {
            "yes": 12392,
            "no": 28199,
            "undecided": 87145,
            "unknown": 0,
            "pyes": 0.029896516375047227,
            "pno": 0.14513608323622945,
            "pundecided": 0.745140077616407,
            "punknown": 0.0,
            "time": 48.17159295082092,
            "percY": 103951531.2,
            "percN": 236550131.4,
            "percU": 731024547.0,
            "percUNK": 0.0,
            "l": 0.029896516375047227,
            "u": 0.8548639167637706
        },
        "~a_7": {
            "yes": 28199,
            "no": 12392,
            "undecided": 87145,
            "unknown": 0,
            "pyes": 0.14513608323622945,
            "pno": 0.029896516375047227,
            "pundecided": 0.745140077616407,
            "punknown": 0.0,
            "time": 48.10269737243652,
            "percY": 236550131.4,
            "percN": 103951531.2,
            "percU": 731024547.0,
            "percUNK": 0.0,
            "l": 0.14513608323622945,
            "u": 0.9701034836249528
        }
    },
    "data": {
        "n_samples": 838860,
        "time": 222.84046983718872,
        "repeated_worlds": 711124,
        "repeated_progs": 838433,
        "unique_progs": 427
    }
}