{
    "status": {
        "d_11": {
            "yes": 47580,
            "no": 0,
            "undecided": 0,
            "unknown": 0,
            "pyes": 0.15205289574151756,
            "pno": 0.0,
            "pundecided": 0.0,
            "punknown": 0.0,
            "time": 7.470057725906372,
            "percY": 24945242.4,
            "percN": 0.0,
            "percU": 0.0,
            "percUNK": 0.0,
            "l": 0.15205289574151756,
            "u": 1.0
        },
        "a_7": {
            "yes": 7407,
            "no": 4500,
            "undecided": 35673,
            "unknown": 0,
            "pyes": 0.14156366507533408,
            "pno": 0.0028202876308208846,
            "pundecided": 0.007668943035363753,
            "punknown": 0.0,
            "time": 7.580290794372559,
            "percY": 3883341.96,
            "percN": 2359260.0,
            "percU": 18702640.44,
            "percUNK": 0.0,
            "l": 0.14156366507533408,
            "u": 0.9971797123691791
        },
        "~a_7": {
            "yes": 4500,
            "no": 7407,
            "undecided": 35673,
            "unknown": 0,
            "pyes": 0.0028202876308208846,
            "pno": 0.14156366507533408,
            "pundecided": 0.007668943035363753,
            "punknown": 0.0,
            "time": 7.721423625946045,
            "percY": 2359260.0,
            "percN": 3883341.96,
            "percU": 18702640.44,
            "percUNK": 0.0,
            "l": 0.0028202876308208846,
            "u": 0.858436334924666
        }
    },
    "data": {
        "n_samples": 52428,
        "time": 44.1474335193634,
        "repeated_worlds": 4848,
        "repeated_progs": 52194,
        "unique_progs": 234
    }
}