{
    "status": {
        "d_12": {
            "yes": 47561,
            "no": 0,
            "undecided": 0,
            "unknown": 0,
            "pyes": 0.14857588372871586,
            "pno": 0.0,
            "pundecided": 0.0,
            "punknown": 0.0,
            "time": 18.259729146957397,
            "percY": 24935281.08,
            "percN": 0.0,
            "percU": 0.0,
            "percUNK": 0.0,
            "l": 0.14857588372871586,
            "u": 1.0
        },
        "a_5": {
            "yes": 11847,
            "no": 0,
            "undecided": 35714,
            "unknown": 0,
            "pyes": 0.002170085944233228,
            "pno": 0.0,
            "pundecided": 0.1464057977844831,
            "punknown": 0.0,
            "time": 18.397002458572388,
            "percY": 6211145.16,
            "percN": 0.0,
            "percU": 18724135.92,
            "percUNK": 0.0,
            "l": 0.002170085944233228,
            "u": 1.0
        },
        "a_8": {
            "yes": 35735,
            "no": 11826,
            "undecided": 0,
            "unknown": 0,
            "pyes": 0.04970588439411999,
            "pno": 0.0988699993345959,
            "pundecided": 0.0,
            "punknown": 0.0,
            "time": 19.031278133392334,
            "percY": 18735145.8,
            "percN": 6200135.28,
            "percU": 0.0,
            "percUNK": 0.0,
            "l": 0.04970588439411999,
            "u": 0.901130000665404
        }
    },
    "data": {
        "n_samples": 52428,
        "time": 78.38448143005371,
        "repeated_worlds": 4867,
        "repeated_progs": 51860,
        "unique_progs": 568
    }
}