{
    "status": {
        "d_14": {
            "yes": 35668,
            "no": 0,
            "undecided": 11820,
            "unknown": 0,
            "pyes": 0.06956830051905759,
            "pno": 0.0,
            "pundecided": 0.0012819119154739587,
            "punknown": 0.0,
            "time": 11.804619312286377,
            "percY": 18700019.04,
            "percN": 0.0,
            "percU": 6196989.6,
            "percUNK": 0.0,
            "l": 0.06956830051905759,
            "u": 1.0
        },
        "~a_6": {
            "yes": 35526,
            "no": 0,
            "undecided": 11962,
            "unknown": 0,
            "pyes": 0.058939694843244815,
            "pno": 0.0,
            "pundecided": 0.01191051759128668,
            "punknown": 0.0,
            "time": 11.878031253814697,
            "percY": 18625571.28,
            "percN": 0.0,
            "percU": 6271437.36,
            "percUNK": 0.0,
            "l": 0.058939694843244815,
            "u": 1.0
        },
        "~a_7": {
            "yes": 30580,
            "no": 4946,
            "undecided": 11962,
            "unknown": 0,
            "pyes": 0.05877949681230639,
            "pno": 0.00016019803093840964,
            "pundecided": 0.01191051759128668,
            "punknown": 0.0,
            "time": 12.178141117095947,
            "percY": 16032482.4,
            "percN": 2593088.88,
            "percU": 6271437.36,
            "percUNK": 0.0,
            "l": 0.05877949681230639,
            "u": 0.9998398019690616
        }
    },
    "data": {
        "n_samples": 52428,
        "time": 55.32470631599426,
        "repeated_worlds": 4940,
        "repeated_progs": 52009,
        "unique_progs": 419
    }
}