{
    "status": {
        "d_13": {
            "yes": 9592,
            "no": 0,
            "undecided": 3192,
            "unknown": 0,
            "pyes": 0.06780055415572656,
            "pno": 0.0,
            "pundecided": 0.0013504489167461343,
            "punknown": 0.0,
            "time": 11.606441736221313,
            "percY": 1257223.44,
            "percN": 0.0,
            "percU": 418375.44,
            "percUNK": 0.0,
            "l": 0.06780055415572656,
            "u": 1.0
        },
        "a_8": {
            "yes": 8889,
            "no": 3895,
            "undecided": 0,
            "unknown": 0,
            "pyes": 0.06783292102221795,
            "pno": 0.0013180820502547656,
            "pundecided": 0.0,
            "punknown": 0.0,
            "time": 12.075185298919678,
            "percY": 1165081.23,
            "percN": 510517.65,
            "percU": 0.0,
            "percUNK": 0.0,
            "l": 0.06783292102221795,
            "u": 0.9986819179497453
        },
        "a_9": {
            "yes": 4060,
            "no": 8724,
            "undecided": 0,
            "unknown": 0,
            "pyes": 0.03437342671734904,
            "pno": 0.03477757635512367,
            "pundecided": 0.0,
            "punknown": 0.0,
            "time": 12.001502752304077,
            "percY": 532144.2,
            "percN": 1143454.68,
            "percU": 0.0,
            "percUNK": 0.0,
            "l": 0.03437342671734904,
            "u": 0.9652224236448763
        }
    },
    "data": {
        "n_samples": 13107,
        "time": 42.11622071266174,
        "repeated_worlds": 323,
        "repeated_progs": 12740,
        "unique_progs": 367
    }
}