{
    "status": {
        "~d_30": {
            "yes": 3584,
            "no": 0,
            "undecided": 0,
            "unknown": 512,
            "pyes": 0.9931599999999976,
            "pno": 0.0,
            "pundecided": 0.0,
            "punknown": 0.006839999999999998,
            "time": 85.33103394508362,
            "percY": 146800.64,
            "percN": 0.0,
            "percU": 0.0,
            "percUNK": 20971.52,
            "l": 0.9931599999999976,
            "u": 1.0,
            "flag": "INTEREST"
        },
        "a_10": {
            "yes": 448,
            "no": 0,
            "undecided": 3520,
            "unknown": 128,
            "pyes": 0.1858999489880989,
            "pno": 0.0,
            "pundecided": 0.8140944056358985,
            "punknown": 5.6453759999999995e-06,
            "time": 84.84735774993896,
            "percY": 18350.08,
            "percN": 0.0,
            "percU": 144179.2,
            "percUNK": 5242.88,
            "l": 0.1858999489880989,
            "u": 1.0
        },
        "a_18": {
            "yes": 132,
            "no": 1691,
            "undecided": 2177,
            "unknown": 96,
            "pyes": 0.00582520151446015,
            "pno": 0.8591816314656032,
            "pundecided": 0.12570036143210378,
            "punknown": 0.009292805587831498,
            "time": 85.88292860984802,
            "percY": 5406.72,
            "percN": 69263.36,
            "percU": 89169.92,
            "percUNK": 3932.16,
            "l": 0.00582520151446015,
            "u": 0.14081836853439678,
            "flag": "INTEREST"
        }
    },
    "data": {
        "n_samples": 4096,
        "time": 263.13187432289124,
        "repeated_worlds": 0,
        "repeated_progs": 14,
        "unique_progs": 4082
    }
}