{
    "status": {
        "d_13": {
            "yes": 122,
            "no": 0,
            "undecided": 65,
            "unknown": 11,
            "pyes": 0.04763158041810028,
            "pno": 0.0,
            "pundecided": 0.00016905450733010005,
            "punknown": 2.7427822614393978e-05,
            "time": 5.6289825439453125,
            "percY": 248.88,
            "percN": 0.0,
            "percU": 132.6,
            "percUNK": 22.44,
            "l": 0.04763158041810028,
            "u": 1.0
        },
        "a_6": {
            "yes": 14,
            "no": 0,
            "undecided": 184,
            "unknown": 0,
            "pyes": 0.0030198914313735283,
            "pno": 0.0,
            "pundecided": 0.04480817131667125,
            "punknown": 0.0,
            "time": 5.546613931655884,
            "percY": 28.56,
            "percN": 0.0,
            "percU": 375.36,
            "percUNK": 0.0,
            "l": 0.0030198914313735283,
            "u": 1.0
        },
        "a_8": {
            "yes": 14,
            "no": 9,
            "undecided": 158,
            "unknown": 17,
            "pyes": 2.8007313895115113e-07,
            "pno": 2.9679690333600007e-10,
            "pundecided": 0.047827089815887056,
            "punknown": 6.925622218729201e-07,
            "time": 5.651264667510986,
            "percY": 28.56,
            "percN": 18.36,
            "percU": 322.32,
            "percUNK": 34.68,
            "l": 2.8007313895115113e-07,
            "u": 0.9999999997032031
        }
    },
    "data": {
        "n_samples": 204,
        "time": 17.122594118118286,
        "repeated_worlds": 6,
        "repeated_progs": 11,
        "unique_progs": 193
    }
}