{
    "status": {
        "~d_14": {
            "yes": 498,
            "no": 0,
            "undecided": 50,
            "unknown": 260,
            "pyes": 0.010977457340848642,
            "pno": 0.0,
            "pundecided": 0.008833458656701312,
            "punknown": 1.3077651110165642,
            "time": 18.461577892303467,
            "percY": 2181.24,
            "percN": 0.0,
            "percU": 219.0,
            "percUNK": 1138.8,
            "l": 0.010977457340848642,
            "u": 1.0
        },
        "a_9": {
            "yes": 180,
            "no": 78,
            "undecided": 460,
            "unknown": 90,
            "pyes": 0.0013857012867952844,
            "pno": 0.0037662092526390507,
            "pundecided": 0.13877158414800764,
            "punknown": 1.1836525323266724,
            "time": 18.415842533111572,
            "percY": 788.4,
            "percN": 341.64,
            "percU": 2014.8,
            "percUNK": 394.2,
            "l": 0.0013857012867952844,
            "u": 0.996233790747361
        },
        "~a_9": {
            "yes": 78,
            "no": 180,
            "undecided": 460,
            "unknown": 90,
            "pyes": 0.0037662092526390507,
            "pno": 0.0013857012867952844,
            "pundecided": 0.13877158414800764,
            "punknown": 1.1836525323266724,
            "time": 18.30024003982544,
            "percY": 341.64,
            "percN": 788.4,
            "percU": 2014.8,
            "percUNK": 394.2,
            "l": 0.0037662092526390507,
            "u": 0.9986142987132047
        }
    },
    "data": {
        "n_samples": 438,
        "time": 40.81978487968445,
        "repeated_programs": 34,
        "inconsistent_programs": 0,
        "worlds_consulted": 751
    }
}