{
    "status": {
        "~d_36": {
            "yes": 177,
            "no": 0,
            "undecided": 210,
            "unknown": 0,
            "pyes": 0.001204069933680849,
            "pno": 0.0,
            "pundecided": 0.5654878230697088,
            "punknown": 0.0,
            "time": 9.459250926971436,
            "percY": 723.93,
            "percN": 0.0,
            "percU": 858.9,
            "percUNK": 0.0,
            "l": 0.001204069933680849,
            "u": 1.0
        },
        "a_14": {
            "yes": 207,
            "no": 101,
            "undecided": 79,
            "unknown": 0,
            "pyes": 0.5628143643801166,
            "pno": 0.001244359187478031,
            "pundecided": 0.002633169435794962,
            "punknown": 0.0,
            "time": 9.931006908416748,
            "percY": 846.63,
            "percN": 413.09,
            "percU": 323.11,
            "percUNK": 0.0,
            "l": 0.5628143643801166,
            "u": 0.998755640812522,
            "flag": "INTEREST"
        },
        "a_17": {
            "yes": 309,
            "no": 78,
            "undecided": 0,
            "unknown": 0,
            "pyes": 0.5666618659182058,
            "pno": 3.002708518396883e-05,
            "pundecided": 0.0,
            "punknown": 0.0,
            "time": 11.902145624160767,
            "percY": 1263.81,
            "percN": 319.02,
            "percU": 0.0,
            "percUNK": 0.0,
            "l": 0.5666618659182058,
            "u": 0.999969972914816,
            "flag": "INTEREST"
        }
    },
    "data": {
        "n_samples": 409,
        "time": 31.739542722702026,
        "repeated_worlds": 22,
        "repeated_progs": 22,
        "unique_progs": 387
    }
}