{
    "em_var": 18,
    "em_var_use_ann": [
        0,
        1,
        2,
        3,
        4,
        5,
        6,
        7,
        8,
        9,
        10,
        11,
        12,
        13,
        14,
        15,
        16,
        17
    ],
    "literals": {
        "0": [
            "a_0",
            "a_1",
            "a_2",
            "a_3",
            "~a_4",
            "a_5",
            "~a_6",
            "a_7",
            "a_8",
            "a_9",
            "a_18",
            "d_21",
            "~d_22",
            "d_23",
            "d_24",
            "d_25",
            "d_26",
            "d_27",
            "~d_28",
            "d_29",
            "d_30",
            "~d_31",
            "~d_32",
            "d_33",
            "~d_34",
            "d_35",
            "~d_36",
            "d_37",
            "d_38",
            "d_39",
            "d_40",
            "d_41",
            "~d_42",
            "d_43",
            "d_44",
            "d_45",
            "~d_46",
            "d_47",
            "~d_48",
            "d_49",
            "d_50",
            "~d_51",
            "d_52",
            "d_53",
            "d_54",
            "~d_55",
            "d_56",
            "d_57",
            "d_58",
            "d_59",
            "d_60",
            "d_61",
            "~d_62",
            "d_63",
            "~d_64",
            "~d_65",
            "d_66",
            "d_67",
            "d_68",
            "~d_69"
        ],
        "1": [
            "a_10",
            "a_11",
            "a_12",
            "a_13",
            "~a_14"
        ],
        "2": [
            "a_15",
            "a_16",
            "a_17",
            "a_19",
            "a_20"
        ],
        "3": [
            "~a_19",
            "~a_19",
            "~a_19",
            "~a_19",
            "a_19",
            "a_19",
            "a_19",
            "a_19",
            "~a_15",
            "~a_15",
            "~a_15",
            "~a_15",
            "a_15",
            "a_15",
            "a_15",
            "a_15",
            "a_15",
            "~a_17",
            "~a_17",
            "~a_17",
            "~a_17",
            "a_17",
            "a_17",
            "a_17",
            "a_17",
            "a_17",
            "a_17",
            "~a_20",
            "~a_20",
            "~a_20",
            "~a_20",
            "a_20",
            "a_20",
            "a_20",
            "a_20",
            "a_20",
            "a_20",
            "~a_16",
            "~a_16",
            "~a_16",
            "~a_16",
            "a_16",
            "a_16",
            "a_16",
            "a_16",
            "a_16",
            "a_16",
            "a_16",
            "a_16"
        ]
    },
    "af": [
        [
            "a_0 -< true;",
            "0 and 1"
        ],
        [
            "a_1 -< true;",
            ""
        ],
        [
            "a_3 -< true;",
            ""
        ],
        [
            "~a_6 -< true;",
            ""
        ],
        [
            "a_8 -< true;",
            ""
        ],
        [
            "d_21 -< true;",
            ""
        ],
        [
            "~d_22 -< true;",
            "3 or 5"
        ],
        [
            "d_23 -< true;",
            "8 and 3"
        ],
        [
            "d_24 -< true;",
            ""
        ],
        [
            "d_25 -< true;",
            "12 or 17"
        ],
        [
            "d_26 -< true;",
            "3 and 10"
        ],
        [
            "d_27 -< true;",
            "11 and 0"
        ],
        [
            "~d_28 -< true;",
            "10 and 0"
        ],
        [
            "d_29 -< true;",
            ""
        ],
        [
            "d_30 -< true;",
            ""
        ],
        [
            "~d_31 -< true;",
            "3 or 12"
        ],
        [
            "~d_32 -< true;",
            ""
        ],
        [
            "d_33 -< true;",
            ""
        ],
        [
            "~d_34 -< true;",
            ""
        ],
        [
            "d_35 -< true;",
            ""
        ],
        [
            "~d_36 -< true;",
            ""
        ],
        [
            "d_37 -< true;",
            ""
        ],
        [
            "d_38 -< true;",
            ""
        ],
        [
            "d_39 -< true;",
            ""
        ],
        [
            "d_40 -< true;",
            ""
        ],
        [
            "d_41 -< true;",
            ""
        ],
        [
            "~d_42 -< true;",
            "12 and 2"
        ],
        [
            "d_43 -< true;",
            ""
        ],
        [
            "d_44 -< true;",
            ""
        ],
        [
            "d_45 -< true;",
            "2 and 12"
        ],
        [
            "~d_46 -< true;",
            ""
        ],
        [
            "d_47 -< true;",
            ""
        ],
        [
            "~d_48 -< true;",
            ""
        ],
        [
            "d_49 -< true;",
            ""
        ],
        [
            "d_50 -< true;",
            ""
        ],
        [
            "~d_51 -< true;",
            ""
        ],
        [
            "d_52 -< true;",
            ""
        ],
        [
            "d_53 -< true;",
            ""
        ],
        [
            "d_54 -< true;",
            "not 3 and 14"
        ],
        [
            "~d_55 -< true;",
            ""
        ],
        [
            "d_56 -< true;",
            "17 or 1"
        ],
        [
            "d_57 -< true;",
            "10 and 7"
        ],
        [
            "d_58 -< true;",
            "5 or 10"
        ],
        [
            "d_59 -< true;",
            ""
        ],
        [
            "d_60 -< true;",
            ""
        ],
        [
            "d_61 -< true;",
            "16 or 14"
        ],
        [
            "~d_62 -< true;",
            ""
        ],
        [
            "d_63 -< true;",
            ""
        ],
        [
            "~d_64 -< true;",
            ""
        ],
        [
            "~d_65 -< true;",
            ""
        ],
        [
            "d_66 -< true;",
            "3 or 4"
        ],
        [
            "d_67 -< true;",
            ""
        ],
        [
            "d_68 -< true;",
            "1 or 17"
        ],
        [
            "~d_69 -< true;",
            "16 or 15"
        ],
        [
            "a_2 <- true;",
            ""
        ],
        [
            "~a_4 <- true;",
            ""
        ],
        [
            "a_5 <- true;",
            "15 and 8"
        ],
        [
            "a_7 <- true;",
            ""
        ],
        [
            "a_9 <- true;",
            ""
        ],
        [
            "a_18 <- true;",
            "12 or 9"
        ],
        [
            "a_13 -< ~a_6,a_0,a_8;",
            "15 and 5"
        ],
        [
            "~a_14 -< a_5;",
            "6 or 0"
        ],
        [
            "a_10 -< ~a_6,a_3;",
            ""
        ],
        [
            "a_12 -< a_8,a_1;",
            "4 and 6"
        ],
        [
            "a_11 -< ~a_6;",
            ""
        ],
        [
            "a_19 -< ~a_14,a_10;",
            "not 1 or 10"
        ],
        [
            "a_15 -< a_12;",
            ""
        ],
        [
            "a_17 -< a_18,a_5,a_11;",
            "0 or 17"
        ],
        [
            "a_20 -< a_13;",
            "10 or 17"
        ],
        [
            "a_16 <- ~a_14,a_12,a_9;",
            ""
        ],
        [
            "~a_19 -< a_10,~a_14,d_21;",
            "16 or 1"
        ],
        [
            "~a_19 -< a_3,~d_22,~a_6;",
            ""
        ],
        [
            "~a_19 -< a_3,~a_6,d_23;",
            ""
        ],
        [
            "~a_19 -< a_10,d_24,~a_14;",
            ""
        ],
        [
            "a_19 -< a_10,d_25,~a_14,d_21;",
            ""
        ],
        [
            "a_19 -< a_3,~d_22,~a_6,d_26;",
            ""
        ],
        [
            "a_19 -< a_3,~a_6,d_23,d_27;",
            ""
        ],
        [
            "a_19 -< a_10,d_24,~d_28,~a_14;",
            "14 or 12"
        ],
        [
            "~a_15 -< a_8,d_29,a_1;",
            "0 or 3"
        ],
        [
            "~a_15 -< a_12,d_30;",
            ""
        ],
        [
            "~a_15 -< ~d_31,a_12;",
            ""
        ],
        [
            "~a_15 -< a_8,~d_32,a_1;",
            "not 4 or 1"
        ],
        [
            "a_15 -< a_8,d_29,a_1,d_33;",
            ""
        ],
        [
            "a_15 -< a_8,~d_34,d_29,a_1;",
            "13 or 9"
        ],
        [
            "a_15 -< d_35,a_12,d_30;",
            "4 or not 7"
        ],
        [
            "a_15 -< ~d_31,~d_36,a_12;",
            ""
        ],
        [
            "a_15 -< a_8,~d_32,a_1,d_37;",
            "6 and 12"
        ],
        [
            "~a_17 -< ~a_6,d_38;",
            ""
        ],
        [
            "~a_17 -< d_39,~a_6;",
            ""
        ],
        [
            "~a_17 -< a_18,d_40,a_5,a_11;",
            ""
        ],
        [
            "~a_17 -< a_18,d_41,a_5,a_11;",
            ""
        ],
        [
            "a_17 -< ~a_6,d_38,~d_42;",
            ""
        ],
        [
            "a_17 -< ~a_6,d_38,d_43;",
            ""
        ],
        [
            "a_17 -< d_39,~a_6,d_44;",
            ""
        ],
        [
            "a_17 -< d_45,d_39,~a_6;",
            "14 and 16"
        ],
        [
            "a_17 -< a_18,a_5,d_40,~d_46,a_11;",
            "13 or 0"
        ],
        [
            "a_17 -< a_18,d_41,a_5,d_47,a_11;",
            ""
        ],
        [
            "~a_20 -< a_13,~d_48;",
            ""
        ],
        [
            "~a_20 -< a_13,d_49;",
            "8 and 11"
        ],
        [
            "~a_20 -< a_13,d_50;",
            "17 or 11"
        ],
        [
            "~a_20 -< a_13,~d_51;",
            ""
        ],
        [
            "a_20 -< a_13,d_52,~d_48;",
            "8 or not 5"
        ],
        [
            "a_20 -< a_13,d_53,~d_48;",
            ""
        ],
        [
            "a_20 -< a_13,d_54,~d_48;",
            "15 and 16"
        ],
        [
            "a_20 -< a_13,d_49,~d_55;",
            ""
        ],
        [
            "a_20 -< d_56,a_13,d_50;",
            ""
        ],
        [
            "a_20 -< a_13,~d_51,d_57;",
            "5 and 8"
        ],
        [
            "~a_16 -< a_8,d_58,a_1;",
            "12 or 0"
        ],
        [
            "~a_16 -< a_8,d_59,a_1;",
            "14 or 3"
        ],
        [
            "~a_16 -< d_60,~a_14,a_12,a_9;",
            ""
        ],
        [
            "~a_16 -< a_8,d_61,a_1;",
            ""
        ],
        [
            "a_16 -< a_8,~d_62,d_58,a_1;",
            ""
        ],
        [
            "a_16 -< a_8,d_63,d_58,a_1;",
            ""
        ],
        [
            "a_16 -< a_8,~d_64,d_58,a_1;",
            "5 or 14"
        ],
        [
            "a_16 -< a_8,~d_65,d_59,a_1;",
            ""
        ],
        [
            "a_16 -< a_8,d_59,a_1,d_66;",
            ""
        ],
        [
            "a_16 -< a_8,d_59,d_67,a_1;",
            "7 or 0"
        ],
        [
            "a_16 -< a_12,a_9,~a_14,d_68,d_60;",
            ""
        ],
        [
            "a_16 -< a_8,d_61,~d_69,a_1;",
            "8 or 14"
        ]
    ]
}