{
    "em_var": 12,
    "em_var_use_ann": [
        0,
        1,
        2,
        3,
        4,
        5,
        6,
        7,
        8,
        9,
        10,
        11
    ],
    "literals": {
        "0": [
            "a_0",
            "a_1",
            "~a_2",
            "a_3",
            "~a_4",
            "a_5",
            "a_6",
            "a_7",
            "a_8",
            "~a_9",
            "~d_18",
            "d_19",
            "d_20",
            "~d_21",
            "d_22",
            "d_23",
            "~d_24",
            "d_25",
            "d_26",
            "d_27",
            "d_28",
            "d_29",
            "~d_30",
            "d_31",
            "d_32",
            "d_33",
            "~d_34",
            "d_35",
            "~d_36",
            "d_37",
            "d_38",
            "d_39",
            "d_40",
            "d_41",
            "~d_42",
            "d_43",
            "~d_44",
            "~d_45",
            "d_46",
            "d_47",
            "d_48",
            "d_49",
            "d_50",
            "d_51",
            "~d_52",
            "d_53",
            "d_54",
            "~d_55",
            "~d_56",
            "d_57",
            "d_58",
            "d_59",
            "d_60",
            "d_61",
            "d_62",
            "d_63",
            "d_64",
            "d_65",
            "d_66",
            "d_67"
        ],
        "1": [
            "~a_10",
            "a_11",
            "a_12",
            "~a_13"
        ],
        "2": [
            "a_14",
            "a_15",
            "a_16",
            "a_17"
        ],
        "3": [
            "~a_14",
            "~a_14",
            "~a_14",
            "~a_14",
            "a_14",
            "a_14",
            "a_14",
            "a_14",
            "a_14",
            "a_14",
            "a_14",
            "a_14",
            "a_14",
            "a_14",
            "~a_16",
            "~a_16",
            "~a_16",
            "~a_16",
            "a_16",
            "a_16",
            "a_16",
            "a_16",
            "a_16",
            "~a_15",
            "~a_15",
            "~a_15",
            "~a_15",
            "a_15",
            "a_15",
            "a_15",
            "a_15",
            "a_15",
            "a_15",
            "a_15",
            "a_15",
            "a_15",
            "a_15",
            "a_15",
            "a_15",
            "~a_17",
            "~a_17",
            "~a_17",
            "~a_17",
            "a_17",
            "a_17",
            "a_17",
            "a_17",
            "a_17",
            "a_17",
            "a_17"
        ]
    },
    "af": [
        [
            "a_0 -< true;",
            "0 or 10 or 9"
        ],
        [
            "~a_4 -< true;",
            "8 and 4 or 6"
        ],
        [
            "a_7 -< true;",
            "3 or 2 or 4"
        ],
        [
            "a_8 -< true;",
            "5 and 3 or 2"
        ],
        [
            "~a_9 -< true;",
            "1 or 10 and 7"
        ],
        [
            "~d_18 -< true;",
            "9 and 7 and 8"
        ],
        [
            "d_19 -< true;",
            "1 and 7 or 6"
        ],
        [
            "d_20 -< true;",
            "not 3 and 9 and 4"
        ],
        [
            "~d_21 -< true;",
            "1 and 2 or 4"
        ],
        [
            "d_22 -< true;",
            "3 and 5 and 7"
        ],
        [
            "d_23 -< true;",
            "2 or not 11 or 9"
        ],
        [
            "~d_24 -< true;",
            "1 and 6 and 5"
        ],
        [
            "d_25 -< true;",
            "1 or 0 or 3"
        ],
        [
            "d_26 -< true;",
            "5 and 0 and 9"
        ],
        [
            "d_27 -< true;",
            "3 and 7 and 0"
        ],
        [
            "d_28 -< true;",
            "8 or 1 or 7"
        ],
        [
            "d_29 -< true;",
            "0 or not 4 and 3"
        ],
        [
            "~d_30 -< true;",
            "3 or 2 or 7"
        ],
        [
            "d_31 -< true;",
            "2 and 7 and 11"
        ],
        [
            "d_32 -< true;",
            "9 or 6 or 5"
        ],
        [
            "d_33 -< true;",
            "9 or 1 or 5"
        ],
        [
            "~d_34 -< true;",
            "not 11 and 10 or 2"
        ],
        [
            "d_35 -< true;",
            "not 4 or 0 and 10"
        ],
        [
            "~d_36 -< true;",
            "8 and 10 or 7"
        ],
        [
            "d_37 -< true;",
            "2 or 8 or 7"
        ],
        [
            "d_38 -< true;",
            "10 or 0 and not 8"
        ],
        [
            "d_39 -< true;",
            "8 or 11 and 1"
        ],
        [
            "d_40 -< true;",
            "10 or 2 or 8"
        ],
        [
            "d_41 -< true;",
            "8 and 3 and 4"
        ],
        [
            "~d_42 -< true;",
            "9 and 2 and 0"
        ],
        [
            "d_43 -< true;",
            "1 and 2 or 4"
        ],
        [
            "~d_44 -< true;",
            "3 or 1 or 10"
        ],
        [
            "~d_45 -< true;",
            "1 and 4 or not 0"
        ],
        [
            "d_46 -< true;",
            "1 or 6 or 10"
        ],
        [
            "d_47 -< true;",
            "9 and 5 and not 0"
        ],
        [
            "d_48 -< true;",
            "11 or 9 and 3"
        ],
        [
            "d_49 -< true;",
            "0 or 11 or 3"
        ],
        [
            "d_50 -< true;",
            "10 and 4 and 8"
        ],
        [
            "d_51 -< true;",
            "3 and 5 or 10"
        ],
        [
            "~d_52 -< true;",
            "9 or 0 and 10"
        ],
        [
            "d_53 -< true;",
            "2 or 6 and 5"
        ],
        [
            "d_54 -< true;",
            "not 1 and 6 or 10"
        ],
        [
            "~d_55 -< true;",
            "5 and 11 or 9"
        ],
        [
            "~d_56 -< true;",
            "9 or 2 or 6"
        ],
        [
            "d_57 -< true;",
            "6 and 8 or 11"
        ],
        [
            "d_58 -< true;",
            "2 and 8 and 9"
        ],
        [
            "d_59 -< true;",
            "not 10 and 8 or 1"
        ],
        [
            "d_60 -< true;",
            "9 or 6 and 2"
        ],
        [
            "d_61 -< true;",
            "2 and 1 or 3"
        ],
        [
            "d_62 -< true;",
            "2 and not 5 or 0"
        ],
        [
            "d_63 -< true;",
            "8 and 7 or 1"
        ],
        [
            "d_64 -< true;",
            "4 and 7 and 10"
        ],
        [
            "d_65 -< true;",
            "not 5 or 6 or 4"
        ],
        [
            "d_66 -< true;",
            "9 and not 10 and 2"
        ],
        [
            "d_67 -< true;",
            "5 or 2 and 0"
        ],
        [
            "a_1 <- true;",
            "6 and not 5 or 11"
        ],
        [
            "~a_2 <- true;",
            "1 or 6 and 10"
        ],
        [
            "a_3 <- true;",
            "5 and 9 and 2"
        ],
        [
            "a_5 <- true;",
            "7 or 3 or 4"
        ],
        [
            "a_6 <- true;",
            "8 or 4 or 11"
        ],
        [
            "~a_13 -< ~a_4,a_0;",
            "5 or not 3 or 0"
        ],
        [
            "~a_10 -< ~a_2;",
            "5 and 10 or 3"
        ],
        [
            "a_11 -< a_7;",
            "8 or 2 or 10"
        ],
        [
            "a_12 <- a_7;",
            "6 or 7 or 5"
        ],
        [
            "a_14 -< ~a_13,~a_10;",
            "not 4 and 10 and 1"
        ],
        [
            "a_16 -< a_12,~a_10;",
            "7 and 3 and 11"
        ],
        [
            "a_15 -< ~a_13,~a_9;",
            "4 or 8 and 2"
        ],
        [
            "a_17 <- ~a_10;",
            "3 or 2 and not 4"
        ],
        [
            "~a_14 -< ~a_2,~d_18;",
            "8 or 3 or 5"
        ],
        [
            "~a_14 -< ~a_2,d_19;",
            "not 6 or 9 and 7"
        ],
        [
            "~a_14 -< a_0,d_20,~a_4;",
            "10 and 6 and 7"
        ],
        [
            "~a_14 -< a_0,~d_21,~a_4;",
            "11 and 3 or 6"
        ],
        [
            "a_14 -< ~a_2,d_22,~d_18;",
            "5 and 7 and 6"
        ],
        [
            "a_14 -< ~a_2,d_23,~d_18;",
            "10 and 3 or 2"
        ],
        [
            "a_14 -< ~a_2,~d_24,~d_18;",
            "5 and 10 or 1"
        ],
        [
            "a_14 -< ~a_2,d_25,d_19;",
            "0 or 4 and 6"
        ],
        [
            "a_14 -< ~a_2,d_19,d_26;",
            "9 and 3 or 4"
        ],
        [
            "a_14 -< ~a_2,d_19,d_27;",
            "4 or 3 or 11"
        ],
        [
            "a_14 -< a_0,d_20,~a_4,d_28;",
            "3 and 4 or 6"
        ],
        [
            "a_14 -< a_0,d_20,d_29,~a_4;",
            "3 and 2 or 9"
        ],
        [
            "a_14 -< a_0,d_20,~a_4,~d_30;",
            "2 and 1 and 5"
        ],
        [
            "a_14 -< a_0,~d_21,d_31,~a_4;",
            "10 and 2 or 9"
        ],
        [
            "~a_16 -< a_7,d_32;",
            "10 and 1 and 9"
        ],
        [
            "~a_16 -< ~a_2,d_33;",
            "5 or 4 or 9"
        ],
        [
            "~a_16 -< ~d_34,~a_10,a_12;",
            "3 or 1 or 9"
        ],
        [
            "~a_16 -< ~a_2,d_35;",
            "4 and 11 and 0"
        ],
        [
            "a_16 -< a_7,~d_36,d_32;",
            "9 and 6 or 5"
        ],
        [
            "a_16 -< a_7,d_32,d_37;",
            "3 or 11 and 2"
        ],
        [
            "a_16 -< ~a_2,d_33,d_38;",
            "6 or 7 and 11"
        ],
        [
            "a_16 -< ~d_34,~a_10,a_12,d_39;",
            "9 and 11 and not 1"
        ],
        [
            "a_16 -< ~a_2,d_40,d_35;",
            "3 and 4 and 8"
        ],
        [
            "~a_15 -< a_0,~a_4,d_41;",
            "4 or 10 or 7"
        ],
        [
            "~a_15 -< ~d_42,~a_9,~a_13;",
            "5 or 9 or 7"
        ],
        [
            "~a_15 -< a_0,d_43,~a_4;",
            "not 3 or 6 or 5"
        ],
        [
            "~a_15 -< ~a_9,~d_44,~a_13;",
            "9 or 11 and 1"
        ],
        [
            "a_15 -< a_0,~a_4,d_41,~d_45;",
            "8 or 6 or 3"
        ],
        [
            "a_15 -< a_0,d_46,~a_4,d_41;",
            "2 and 9 or 8"
        ],
        [
            "a_15 -< a_0,d_47,~a_4,d_41;",
            "1 and 5 and not 4"
        ],
        [
            "a_15 -< a_0,d_48,~a_4,d_41;",
            "not 2 and 9 and 4"
        ],
        [
            "a_15 -< d_49,~d_42,~a_9,~a_13;",
            "2 and 6 or 9"
        ],
        [
            "a_15 -< ~d_42,~a_9,~a_13,d_50;",
            "11 or 0 or 8"
        ],
        [
            "a_15 -< ~d_42,~a_9,d_51,~a_13;",
            "3 and 7 and 1"
        ],
        [
            "a_15 -< a_0,d_43,~a_4,~d_52;",
            "3 or 0 or 9"
        ],
        [
            "a_15 -< a_0,d_43,~a_4,d_53;",
            "1 or 10 and 0"
        ],
        [
            "a_15 -< a_0,d_43,~a_4,d_54;",
            "4 or 10 and 2"
        ],
        [
            "a_15 -< ~a_9,~d_44,~a_13,~d_55;",
            "4 or 3 or 2"
        ],
        [
            "a_15 -< ~a_9,~d_44,~d_56,~a_13;",
            "3 and 5 and 1"
        ],
        [
            "~a_17 -< d_57,~a_10;",
            "2 or 4 or 8"
        ],
        [
            "~a_17 -< ~a_10,d_58;",
            "6 or 7 or 4"
        ],
        [
            "~a_17 -< ~a_2,d_59;",
            "9 or 5 or 4"
        ],
        [
            "~a_17 -< ~a_2,d_60;",
            "1 or 9 and 11"
        ],
        [
            "a_17 -< d_57,~a_10,d_61;",
            "9 and 11 or 2"
        ],
        [
            "a_17 -< d_57,~a_10,d_62;",
            "4 or not 0 and 7"
        ],
        [
            "a_17 -< d_57,d_63,~a_10;",
            "7 or not 9 or 11"
        ],
        [
            "a_17 -< d_64,d_57,~a_10;",
            "5 and 10 or 0"
        ],
        [
            "a_17 -< d_65,~a_10,d_58;",
            "4 and 6 or 7"
        ],
        [
            "a_17 -< ~a_2,d_66,d_59;",
            "0 or 10 or 5"
        ],
        [
            "a_17 -< ~a_2,d_60,d_67;",
            "1 or 10 and 2"
        ]
    ]
}